formfyxer/__init__.py
formfyxer/docassemble_support.py
formfyxer/docx_wrangling.py
formfyxer/lit_explorer.py
formfyxer/passive_voice_detection.py
formfyxer/pdf_wrangling.py
formfyxer/py.typed
formfyxer/requirements.txt
formfyxer/data/gendered_terms.yml
formfyxer/data/simplified_words.yml
formfyxer/prompts/describe_form.txt
formfyxer/prompts/field_grouping.txt
formfyxer/prompts/field_labeling.txt
formfyxer/prompts/guess_form_name.txt
formfyxer/prompts/normalize_field_name.txt
formfyxer/prompts/passive_voice.txt
formfyxer/prompts/plain_language.txt
formfyxer-1.0.1.dist-info/licenses/LICENSE
formfyxer-1.0.1.dist-info/METADATA
formfyxer-1.0.1.dist-info/WHEEL
formfyxer-1.0.1.dist-info/entry_points.txt
formfyxer-1.0.1.dist-info/top_level.txt
formfyxer-1.0.1.dist-info/RECORD
