Metadata-Version: 2.4
Name: formfyxer
Version: 1.0.1
Summary: A tool for learning about and pre-processing pdf forms.
Home-page: https://github.com/SuffolkLITLab/FormFyxer
Author: Suffolk LIT Lab
Author-email: litlab@suffolk.edu
License: MIT
Project-URL: Bug Tracker, https://github.com/SuffolkLITLab/FormFyxer/issues
License-File: LICENSE
Requires-Dist: pdfminer.six
Requires-Dist: pandas
Requires-Dist: pikepdf
Requires-Dist: textstat
Requires-Dist: requests
Requires-Dist: numpy
Requires-Dist: boxdetect
Requires-Dist: pdf2image
Requires-Dist: reportlab>=3.6.13
Requires-Dist: pdfminer.six
Requires-Dist: opencv-python-headless
Requires-Dist: ocrmypdf
Requires-Dist: eyecite
Requires-Dist: sigfig
Requires-Dist: openai
Requires-Dist: python-dotenv
Requires-Dist: python-docx
Requires-Dist: tiktoken
Requires-Dist: transformers
Dynamic: author
Dynamic: author-email
Dynamic: description
Dynamic: description-content-type
Dynamic: home-page
Dynamic: license
Dynamic: license-file
Dynamic: project-url
Dynamic: requires-dist
Dynamic: summary
